uvd_x402_sdk/__init__.py
uvd_x402_sdk/client.py
uvd_x402_sdk/config.py
uvd_x402_sdk/decorators.py
uvd_x402_sdk/exceptions.py
uvd_x402_sdk/facilitator.py
uvd_x402_sdk/models.py
uvd_x402_sdk/response.py
uvd_x402_sdk/integrations/__init__.py
uvd_x402_sdk/integrations/django_integration.py
uvd_x402_sdk/integrations/fastapi_integration.py
uvd_x402_sdk/integrations/flask_integration.py
uvd_x402_sdk/integrations/lambda_integration.py
uvd_x402_sdk/networks/__init__.py
uvd_x402_sdk/networks/algorand.py
uvd_x402_sdk/networks/base.py
uvd_x402_sdk/networks/evm.py
uvd_x402_sdk/networks/near.py
uvd_x402_sdk/networks/solana.py
uvd_x402_sdk/networks/stellar.py
uvd_x402_sdk/networks/sui.py
uvd_x402_sdk-0.5.6.dist-info/LICENSE
uvd_x402_sdk-0.5.6.dist-info/METADATA
uvd_x402_sdk-0.5.6.dist-info/WHEEL
uvd_x402_sdk-0.5.6.dist-info/top_level.txt
uvd_x402_sdk-0.5.6.dist-info/RECORD
