Metadata-Version: 2.1
Name: uvd-x402-sdk
Version: 0.5.6
Summary: Python SDK for x402 payments - gasless crypto payments across 18 blockchains with multi-stablecoin support (USDC, EURC, AUSD, PYUSD, USDT)
Author-email: Ultravioleta DAO <dev@ultravioletadao.xyz>
Project-URL: Homepage, https://github.com/UltravioletaDAO/uvd-x402-sdk-python
Project-URL: Documentation, https://docs.ultravioletadao.xyz/x402-sdk
Project-URL: Repository, https://github.com/UltravioletaDAO/uvd-x402-sdk-python
Project-URL: Issues, https://github.com/UltravioletaDAO/uvd-x402-sdk-python/issues
Keywords: x402,payments,crypto,usdc,eurc,stablecoin,web3,evm,solana,near,stellar,algorand,sui,facilitator,gasless,eip-712,eip-3009
Classifier: Development Status :: 4 - Beta
Classifier: Intended Audience :: Developers
Classifier: License :: OSI Approved :: MIT License
Classifier: Operating System :: OS Independent
Classifier: Programming Language :: Python :: 3
Classifier: Programming Language :: Python :: 3.9
Classifier: Programming Language :: Python :: 3.10
Classifier: Programming Language :: Python :: 3.11
Classifier: Programming Language :: Python :: 3.12
Classifier: Topic :: Software Development :: Libraries :: Python Modules
Classifier: Topic :: Office/Business :: Financial :: Point-Of-Sale
Requires-Python: >=3.9
License-File: LICENSE
Requires-Dist: httpx>=0.24.0
Requires-Dist: pydantic>=2.0.0
Provides-Extra: algorand
Requires-Dist: py-algorand-sdk>=2.0.0; extra == "algorand"
Provides-Extra: all
Requires-Dist: uvd-x402-sdk[algorand,aws,django,fastapi,flask,web3]; extra == "all"
Provides-Extra: aws
Requires-Dist: boto3>=1.26.0; extra == "aws"
Provides-Extra: dev
Requires-Dist: pytest>=7.0.0; extra == "dev"
Requires-Dist: pytest-asyncio>=0.21.0; extra == "dev"
Requires-Dist: pytest-cov>=4.0.0; extra == "dev"
Requires-Dist: black>=23.0.0; extra == "dev"
Requires-Dist: ruff>=0.1.0; extra == "dev"
Requires-Dist: mypy>=1.0.0; extra == "dev"
Requires-Dist: httpx>=0.24.0; extra == "dev"
Provides-Extra: django
Requires-Dist: django>=4.0.0; extra == "django"
Provides-Extra: fastapi
Requires-Dist: fastapi>=0.100.0; extra == "fastapi"
Requires-Dist: starlette>=0.27.0; extra == "fastapi"
Provides-Extra: flask
Requires-Dist: flask>=2.0.0; extra == "flask"
Provides-Extra: web3
Requires-Dist: web3>=6.0.0; extra == "web3"
Requires-Dist: eth-account>=0.10.0; extra == "web3"
